pytest_multilog/__init__.py
pytest_multilog/helper.py
pytest_multilog-1.6.1.dist-info/licenses/LICENSE
pytest_multilog-1.6.1.dist-info/METADATA
pytest_multilog-1.6.1.dist-info/WHEEL
pytest_multilog-1.6.1.dist-info/top_level.txt
pytest_multilog-1.6.1.dist-info/RECORD
