Metadata-Version: 2.4
Name: pytest-multilog
Version: 1.6.1
Summary: Multi-process logs handling and other helpers for pytest
Author: The dynod project
Maintainer: The dynod project
License: MIT License
Project-URL: Homepage, https://github.com/dynod/pytest-multilog
Project-URL: Repository, https://github.com/dynod/pytest-multilog
Project-URL: Issues, https://github.com/dynod/pytest-multilog/issues?q=is%3Aopen+is%3Aissue
Classifier: Programming Language :: Python :: 3.10
Classifier: Programming Language :: Python :: 3.11
Classifier: Programming Language :: Python :: 3.12
Classifier: Programming Language :: Python :: 3.13
Classifier: Programming Language :: Python :: 3.14
Requires-Python: >=3.10
License-File: LICENSE
Requires-Dist: pytest
Requires-Dist: pytest-xdist
Requires-Dist: pathvalidate
Dynamic: license-file
